thinkscribe/__init__.py
thinkscribe/generator.py
thinkscribe/html_renderer.py
thinkscribe/markdown_llm.py
thinkscribe/pdf_renderer.py
thinkscribe/prompts.py
thinkscribe/regex.py
thinkscribe/report_config.py
thinkscribe/serializers.py
thinkscribe/styles.py
thinkscribe/config/__init__.py
thinkscribe/config/logging.py
thinkscribe/config/settings.py
thinkscribe/prompts/prompt_templates.yaml
thinkscribe/styles/styles.css
thinkscribe/utils/__init__.py
thinkscribe/utils/async_utils.py
thinkscribe/utils/paths.py
thinkscribe-1.0.dist-info/licenses/LICENSE
thinkscribe-1.0.dist-info/METADATA
thinkscribe-1.0.dist-info/WHEEL
thinkscribe-1.0.dist-info/top_level.txt
thinkscribe-1.0.dist-info/RECORD
