Metadata-Version: 2.4
Name: thinkscribe
Version: 1.0
Summary: Transform your thoughts into beautiful visual reports — give us abstract text, we create meaning with charts and diagrams
Author-email: Muhmmad Abrar Raja Mohamed <muhmmadabrar159@gmail.com>
License: MIT
Project-URL: Homepage, https://github.com/yourusername/thinkscribe
Project-URL: Documentation, https://github.com/yourusername/thinkscribe#readme
Project-URL: Repository, https://github.com/yourusername/thinkscribe
Project-URL: Issues, https://github.com/yourusername/thinkscribe/issues
Keywords: report,pdf,llm,mermaid,chartjs,data-visualization,ollama,openai
Classifier: Development Status :: 3 - Alpha
Classifier: Intended Audience :: Developers
Classifier: License :: OSI Approved :: MIT License
Classifier: Programming Language :: Python :: 3
Classifier: Programming Language :: Python :: 3.10
Classifier: Programming Language :: Python :: 3.11
Classifier: Programming Language :: Python :: 3.12
Classifier: Topic :: Software Development :: Libraries :: Python Modules
Classifier: Topic :: Office/Business
Requires-Python: >=3.10
License-File: LICENSE
Requires-Dist: markdown>=3.4
Requires-Dist: requests>=2.31
Requires-Dist: pyyaml>=6.0
Requires-Dist: playwright>=1.40
Requires-Dist: pydantic>=2.0
Requires-Dist: pydantic-settings>=2.0
Provides-Extra: dev
Requires-Dist: pytest>=7.4; extra == "dev"
Requires-Dist: pytest-cov>=4.1; extra == "dev"
Requires-Dist: black>=23.0; extra == "dev"
Requires-Dist: ruff>=0.1; extra == "dev"
Dynamic: license-file
